pulgon_tools/Irreps_tables.py
pulgon_tools/Irreps_tables_withparities.py
pulgon_tools/__init__.py
pulgon_tools/detect_generalized_translational_group.py
pulgon_tools/detect_point_group.py
pulgon_tools/force_constant_correction.py
pulgon_tools/generate_MoS2type_nanotube.py
pulgon_tools/generate_structures.py
pulgon_tools/line_group_table.py
pulgon_tools/test.py
pulgon_tools/utils.py
pulgon_tools/scripts/pulgon-detect-AxialPointGroup.py
pulgon_tools/scripts/pulgon-detect-CyclicGroup.py
pulgon_tools/scripts/pulgon-fcs-correction.py
pulgon_tools/scripts/pulgon-generate-structures.py
pulgon_tools-2023.10.1.dist-info/licenses/AUTHORS
pulgon_tools-2023.10.1.dist-info/licenses/LICENSE
pulgon_tools-2023.10.1.dist-info/METADATA
pulgon_tools-2023.10.1.dist-info/WHEEL
pulgon_tools-2023.10.1.dist-info/entry_points.txt
pulgon_tools-2023.10.1.dist-info/top_level.txt
pulgon_tools-2023.10.1.dist-info/RECORD
