Metadata-Version: 2.4
Name: pulgon_tools
Version: 2023.10.1
Summary: Work-in-progress foundation libraries of the PULGON project
Author-email: Yujie Cen <yujie.cen@tuwien.ac.at>
Classifier: Programming Language :: Python :: 3
Classifier: Operating System :: OS Independent
Requires-Python: <3.11,>=3.9
License-File: LICENSE
License-File: AUTHORS
Requires-Dist: numpy
Requires-Dist: ase
Requires-Dist: pymatgen
Requires-Dist: ipdb
Requires-Dist: cvxpy
Requires-Dist: phonopy
Requires-Dist: seekpath
Provides-Extra: test
Requires-Dist: pytest; extra == "test"
Requires-Dist: pytest-datadir; extra == "test"
Dynamic: license-file
